{"nodes": [{"id": "docs_v3_decisions_sprint_5_linkrule", "label": "linkRule creates rule in rules table post-cutover (D5.1)", "file_type": "concept", "source_file": "docs/v3/DECISIONS_SPRINT_5.md", "source_location": null, "source_url": null, "captured_at": null, "author": null, "contributor": null}, {"id": "docs_v3_decisions_sprint_5_pretrade_enforceable", "label": "Only propose rules for pre-trade enforceable metrics (D5.2)", "file_type": "rationale", "source_file": "docs/v3/DECISIONS_SPRINT_5.md", "source_location": null, "source_url": null, "captured_at": null, "author": null, "contributor": null}, {"id": "docs_v3_decisions_sprint_5_suggestrules", "label": "Idempotent suggestRulesFromInsights (D5.4)", "file_type": "concept", "source_file": "docs/v3/DECISIONS_SPRINT_5.md", "source_location": null, "source_url": null, "captured_at": null, "author": null, "contributor": null}], "edges": [{"source": "docs_v3_decisions_sprint_5_linkrule", "target": "docs_v3_gates_g1_g2_biz1_g2", "relation": "references", "confidence": "EXTRACTED", "confidence_score": 1.0, "source_file": "docs/v3/DECISIONS_SPRINT_5.md", "source_location": null, "weight": 1.0}, {"source": "docs_v3_decisions_sprint_5_suggestrules", "target": "docs_v3_master_prd_e1_behavior_engine", "relation": "implements", "confidence": "INFERRED", "confidence_score": 0.75, "source_file": "docs/v3/DECISIONS_SPRINT_5.md", "source_location": null, "weight": 1.0}, {"source": "docs_v3_decisions_sprint_5_pretrade_enforceable", "target": "docs_v3_decisions_sprint_1_classifymode", "relation": "conceptually_related_to", "confidence": "INFERRED", "confidence_score": 0.65, "source_file": "docs/v3/DECISIONS_SPRINT_5.md", "source_location": null, "weight": 1.0}, {"source": "docs_v3_decisions_sprint_1_gated_templates", "target": "docs_v3_decisions_sprint_5_pretrade_enforceable", "relation": "semantically_similar_to", "confidence": "INFERRED", "confidence_score": 0.8, "source_file": "docs/v3/DECISIONS_SPRINT_5.md", "source_location": null, "weight": 1.0}], "hyperedges": []}